{
  "cli": {
    "version": ">= 16.28.0",
    "appVersionSource": "remote"
  },
  "build": {
    "development": {
      "developmentClient": true,
      "distribution": "internal",
      "node": "20.18.0",
      "channel": "development",
      "ios": {
        "image": "latest"
      }
    },
    "preview": {
      "distribution": "internal",
      "android": {
        "buildType": "apk"
      },
      "node": "20.18.0",
      "channel": "preview",
      "ios": {
        "image": "latest"
      }
    },
    "preview-apk": {
      "distribution": "internal",
      "android": {
        "buildType": "apk",
        "gradleCommand": ":app:assembleRelease"
      },
      "node": "20.18.0",
      "channel": "preview"
    },
    "production": {
      "autoIncrement": true,
      "node": "20.18.0",
      "channel": "production",
      "ios": {
        "image": "macos-sequoia-15.4-xcode-16.3"
      }
    }
  },
  "submit": {
    "production": {
      "ios": {
        "ascAppId": "6757980969"
      }
    }
  }
}
